{
  "userId": 37254,
  "cartId": "e1c8ef74-8f91-426c-ab1a-3480639ec7ac",
  "preferredProducts": [
    1604
  ],
  "productReviews": [
    {
      "productId": 4341,
      "reviewText": "heard about this on hip-hop music radio, decided to give it a try.",
      "reviewDate": "2016-08-19T21:13:25.3049391+03:00"
    },
    {
      "productId": 4140,
      "reviewText": "i use it daily when i'm in my outhouse.",
      "reviewDate": "2019-05-21T20:46:08.8195895+03:00"
    },
    {
      "productId": 264,
      "reviewText": "this Balanced is gracious.",
      "reviewDate": "2018-12-20T15:16:31.6802379+02:00"
    },
    {
      "productId": 3664,
      "reviewText": "I saw one of these in Tanzania and I bought one.",
      "reviewDate": "2016-06-02T07:40:01.3492997+03:00"
    }
  ]
}