{
  "userId": 19323,
  "cartId": "03533734-01a2-4bd3-b64e-3ccf02f99f34",
  "preferredProducts": [
    2315,
    2964,
    169,
    1719
  ],
  "productReviews": [
    {
      "productId": 1139,
      "reviewText": "My neighbor Georgie has one of these. She works as a busboy and she says it looks brown.",
      "reviewDate": "2018-06-24T02:17:33.3977302+03:00"
    },
    {
      "productId": 2003,
      "reviewText": "I saw one of these in Haiti and I bought one.",
      "reviewDate": "2019-01-01T11:19:26.2684+02:00"
    }
  ]
}