{
  "userId": 52036,
  "cartId": "c59d2a52-15f6-4f4e-9535-9b01fc227213",
  "preferredProducts": [
    2708,
    3072,
    2110,
    2773,
    3983,
    872,
    1069,
    1161,
    518,
    3898
  ],
  "productReviews": [
    {
      "productId": 439,
      "reviewText": "My co-worker Mohamed has one of these. He says it looks brown.",
      "reviewDate": "2016-12-25T16:32:10.784393+02:00"
    },
    {
      "productId": 3069,
      "reviewText": "This Technician works really well. It wildly improves my baseball by a lot.",
      "reviewDate": "2016-11-30T17:20:20.9804734+02:00"
    },
    {
      "productId": 4055,
      "reviewText": "My co-worker Matthew has one of these. He says it looks gigantic.",
      "reviewDate": "2017-09-04T18:33:32.0899552+03:00"
    },
    {
      "productId": 4705,
      "reviewText": "My vulture loves to play with it.",
      "reviewDate": "2017-07-12T03:42:36.309634+03:00"
    },
    {
      "productId": 4173,
      "reviewText": "My co-worker Mohamed has one of these. He says it looks brown.",
      "reviewDate": "2019-11-22T14:06:44.9721129+02:00"
    }
  ]
}