{
  "userId": 39945,
  "cartId": "728ac265-44b3-4d74-b965-a7f2a02c39f3",
  "preferredProducts": [
    2255,
    1282,
    3597,
    2556,
    1921,
    2954
  ],
  "productReviews": [
    {
      "productId": 3824,
      "reviewText": "This California works certainly well. It excitedly improves my football by a lot.",
      "reviewDate": "2019-07-11T04:11:32.6842125+03:00"
    },
    {
      "productId": 1571,
      "reviewText": "The box this comes in is 3 inch by 6 centimeter and weights 15 ounce!",
      "reviewDate": "2018-01-01T00:41:09.3287028+02:00"
    },
    {
      "productId": 581,
      "reviewText": "one of my hobbies is baking. and when i'm baking this works great.",
      "reviewDate": "2018-08-08T16:12:53.9108372+03:00"
    },
    {
      "productId": 4506,
      "reviewText": "My co-worker Skylar has one of these. He says it looks sweaty.",
      "reviewDate": "2017-01-01T11:21:51.1860499+02:00"
    },
    {
      "productId": 2572,
      "reviewText": "My scarab beetle loves to play with it.",
      "reviewDate": "2016-08-07T06:54:09.437328+03:00"
    }
  ]
}