{
  "userId": 72386,
  "cartId": "d1664f17-1722-45c1-86b8-7dfca8b0977d",
  "preferredProducts": [
    4485,
    1685,
    4939,
    4128,
    1632,
    1684,
    1965,
    3833,
    2751
  ],
  "productReviews": [
    {
      "productId": 3625,
      "reviewText": "heard about this on songo radio, decided to give it a try.",
      "reviewDate": "2017-02-25T13:30:11.7282341+02:00"
    },
    {
      "productId": 3482,
      "reviewText": "talk about pleasure!",
      "reviewDate": "2016-05-26T07:24:23.9482503+03:00"
    },
    {
      "productId": 4052,
      "reviewText": "one of my hobbies is drawing. and when i'm drawing this works great.",
      "reviewDate": "2019-07-24T07:07:40.8357076+03:00"
    }
  ]
}