{
  "userId": 72657,
  "cartId": "eaa4d703-a8d0-4ff9-a5ee-94d79e090438",
  "preferredProducts": [
    2509,
    3426,
    1266,
    1617
  ],
  "productReviews": [
    {
      "productId": 978,
      "reviewText": "This navigating works quite well. It romantically improves my golf by a lot.",
      "reviewDate": "2017-05-27T08:39:32.1463588+03:00"
    },
    {
      "productId": 3829,
      "reviewText": "talk about bliss!!",
      "reviewDate": "2017-05-17T10:29:49.8146153+03:00"
    },
    {
      "productId": 690,
      "reviewText": "I saw one of these in Vanuatu and I bought one.",
      "reviewDate": "2018-08-04T18:02:50.5535069+03:00"
    },
    {
      "productId": 3212,
      "reviewText": "My neighbor Frona has one of these. She works as a gambler and she says it looks bearded.",
      "reviewDate": "2017-05-11T19:28:18.5590119+03:00"
    },
    {
      "productId": 750,
      "reviewText": "My neighbor Eller has one of these. She works as a butler and she says it looks smoky.",
      "reviewDate": "2020-04-01T06:36:55.2688172+03:00"
    }
  ]
}