{
  "userId": 72019,
  "cartId": "1bb10ffa-82c1-45e8-a7ed-7fa80d0a5753",
  "preferredProducts": [
    3109,
    4554
  ],
  "productReviews": [
    {
      "productId": 427,
      "reviewText": "i use it occasionally when i'm in my outhouse.",
      "reviewDate": "2018-01-16T03:40:31.1981829+02:00"
    },
    {
      "productId": 4072,
      "reviewText": "one of my hobbies is skateboarding. and when i'm skateboarding this works great.",
      "reviewDate": "2016-06-03T02:34:02.1935578+03:00"
    },
    {
      "productId": 1651,
      "reviewText": "My neighbor Montserrat has one of these. She works as a circus performer and she says it looks shriveled.",
      "reviewDate": "2019-05-29T09:22:44.1316167+03:00"
    }
  ]
}