{
  "userId": 98039,
  "cartId": "f477cb9c-5bb3-4c4f-81ac-ce90d6dd2123",
  "preferredProducts": [
    2189,
    1029,
    2544,
    491,
    4034
  ],
  "productReviews": [
    {
      "productId": 972,
      "reviewText": "It only works when I'm Niue.",
      "reviewDate": "2019-05-06T05:49:49.5284195+03:00"
    },
    {
      "productId": 3096,
      "reviewText": "heard about this on balearic beat radio, decided to give it a try.",
      "reviewDate": "2017-01-13T14:46:50.7041911+02:00"
    },
    {
      "productId": 1299,
      "reviewText": "This Investor works outstandingly well. It grudgingly improves my baseball by a lot.",
      "reviewDate": "2017-12-16T13:24:12.6134832+02:00"
    },
    {
      "productId": 1572,
      "reviewText": "heard about this on smooth jazz radio, decided to give it a try.",
      "reviewDate": "2019-10-21T20:02:35.6800253+03:00"
    },
    {
      "productId": 2831,
      "reviewText": "My neighbor Betha has one of these. She works as a teacher and she says it looks wide.",
      "reviewDate": "2020-02-15T07:44:18.2325302+02:00"
    }
  ]
}