{
  "userId": 98582,
  "cartId": "8d002239-25e9-4e86-9587-a7d2175d1af6",
  "preferredProducts": [
    3320
  ],
  "productReviews": [
    {
      "productId": 1218,
      "reviewText": "The box this comes in is 3 yard by 6 light-year and weights 11 megaton!!",
      "reviewDate": "2019-10-09T13:12:03.760706+03:00"
    },
    {
      "productId": 1641,
      "reviewText": "My co-worker Matthew has one of these. He says it looks gigantic.",
      "reviewDate": "2019-02-16T13:58:57.8445946+02:00"
    }
  ]
}