{
  "userId": 98032,
  "cartId": "c474b5f1-0e67-4187-8631-7cf24548854c",
  "preferredProducts": [
    2100,
    2371,
    1956,
    643,
    667,
    4408,
    4617
  ],
  "productReviews": [
    {
      "productId": 2966,
      "reviewText": "talk about irritation.",
      "reviewDate": "2019-08-26T10:33:28.2217124+03:00"
    },
    {
      "productId": 2483,
      "reviewText": "heard about this on jump-up radio, decided to give it a try.",
      "reviewDate": "2020-03-07T18:21:04.9728031+02:00"
    },
    {
      "productId": 1472,
      "reviewText": "My neighbor Lular has one of these. She works as a cake decorator and she says it looks ragged.",
      "reviewDate": "2018-04-09T13:29:11.462287+03:00"
    },
    {
      "productId": 1905,
      "reviewText": "i use it barely when i'm in my store.",
      "reviewDate": "2018-08-13T20:36:13.1375784+03:00"
    }
  ]
}