{
  "userId": 18132,
  "cartId": "e592153e-32ab-4aa8-889c-60b9141e1447",
  "preferredProducts": [
    4273,
    258,
    2515,
    1708,
    2883,
    1399,
    3332
  ],
  "productReviews": [
    {
      "productId": 1419,
      "reviewText": "This deliverables works very well. It harmonically improves my tennis by a lot.",
      "reviewDate": "2016-12-03T02:08:03.7401163+02:00"
    },
    {
      "productId": 1897,
      "reviewText": "heard about this on balearic beat radio, decided to give it a try.",
      "reviewDate": "2016-08-09T10:41:17.6104743+03:00"
    }
  ]
}