{
  "userId": 4242,
  "cartId": "b1f0ecd5-ec30-42e7-b6e2-cccbc48489e1",
  "preferredProducts": [
    1170
  ],
  "productReviews": [
    {
      "productId": 781,
      "reviewText": "i use it every Tuesday when i'm in my homeless shelter.",
      "reviewDate": "2016-10-09T12:12:09.4896603+03:00"
    },
    {
      "productId": 2716,
      "reviewText": "The box this comes in is 5 light-year by 6 foot and weights 17 megaton!!!",
      "reviewDate": "2018-08-12T02:48:12.7090318+03:00"
    }
  ]
}