{
  "userId": 27745,
  "cartId": "bd92dae9-7fea-4272-8530-f7d2a28d46ba",
  "preferredProducts": [],
  "productReviews": [
    {
      "productId": 3105,
      "reviewText": "My neighbor Aldona has one of these. She works as a butler and she says it looks humongous.",
      "reviewDate": "2020-04-12T10:07:21.4185877+03:00"
    },
    {
      "productId": 2615,
      "reviewText": "The box this comes in is 4 yard by 5 inch and weights 12 pound!",
      "reviewDate": "2016-12-13T07:04:35.2585588+02:00"
    },
    {
      "productId": 844,
      "reviewText": "heard about this on timba radio, decided to give it a try.",
      "reviewDate": "2020-01-04T18:24:06.2673308+02:00"
    }
  ]
}