{
  "userId": 27469,
  "cartId": "65be2faf-763b-41dc-9b50-e8dd5684b895",
  "preferredProducts": [
    2532,
    400
  ],
  "productReviews": [
    {
      "productId": 1602,
      "reviewText": "This Passage works very well. It romantically improves my football by a lot.",
      "reviewDate": "2016-08-17T11:42:57.0324811+03:00"
    },
    {
      "productId": 2044,
      "reviewText": "i use it occasionally when i'm in my outhouse.",
      "reviewDate": "2017-10-26T01:45:23.9154189+03:00"
    }
  ]
}