{
  "userId": 66958,
  "cartId": "d148a02b-5fae-402d-9b66-801b2615defa",
  "preferredProducts": [
    3090,
    2955,
    4935,
    2568,
    1394,
    865,
    1513,
    2170
  ],
  "productReviews": [
    {
      "productId": 1280,
      "reviewText": "My neighbor Frona has one of these. She works as a gambler and she says it looks bearded.",
      "reviewDate": "2017-05-07T09:01:59.0622322+03:00"
    },
    {
      "productId": 1970,
      "reviewText": "this Intelligent is smooth.",
      "reviewDate": "2019-09-10T20:11:02.9414037+03:00"
    },
    {
      "productId": 3076,
      "reviewText": "this bypass is revolting.",
      "reviewDate": "2019-12-09T16:13:09.9305874+02:00"
    },
    {
      "productId": 4591,
      "reviewText": "It only works when I'm Niger.",
      "reviewDate": "2016-05-13T01:22:45.8831046+03:00"
    }
  ]
}