{
  "userId": 20880,
  "cartId": "1cb61419-2b84-42f0-acfe-f0c71a8317cf",
  "preferredProducts": [
    1862,
    121
  ],
  "productReviews": [
    {
      "productId": 2782,
      "reviewText": "It only works when I'm Singapore.",
      "reviewDate": "2016-12-11T18:42:59.890819+02:00"
    },
    {
      "productId": 4179,
      "reviewText": "The box this comes in is 3 yard by 6 yard and weights 19 pound!!!",
      "reviewDate": "2019-02-13T11:53:04.674479+02:00"
    },
    {
      "productId": 86,
      "reviewText": "talk about bliss!!",
      "reviewDate": "2020-04-29T16:17:19.3504723+03:00"
    },
    {
      "productId": 4335,
      "reviewText": "i use it for 10 weeks when i'm in my jail.",
      "reviewDate": "2017-11-05T08:11:19.0055523+02:00"
    }
  ]
}