{
  "userId": 11214,
  "cartId": "881c7731-d3aa-4881-a7cf-86116f5f4eb8",
  "preferredProducts": [
    998
  ],
  "productReviews": [
    {
      "productId": 2499,
      "reviewText": "My gentoo penguin loves to play with it.",
      "reviewDate": "2017-10-29T23:21:58.4715453+02:00"
    },
    {
      "productId": 4957,
      "reviewText": "heard about this on chicha radio, decided to give it a try.",
      "reviewDate": "2020-01-12T15:16:35.0361084+02:00"
    },
    {
      "productId": 1556,
      "reviewText": "this Nepalese Rupee is complimentary.",
      "reviewDate": "2020-02-12T03:37:15.8551915+02:00"
    },
    {
      "productId": 3122,
      "reviewText": "This Bedfordshire works considerably well. It mildly improves my basketball by a lot.",
      "reviewDate": "2018-08-16T05:29:26.9014498+03:00"
    }
  ]
}