{
  "userId": 11160,
  "cartId": "3542cafb-67bd-4d34-ad54-8a2c443c3812",
  "preferredProducts": [
    4607,
    3970,
    85,
    2357,
    4977,
    757,
    123,
    1644,
    2375
  ],
  "productReviews": [
    {
      "productId": 1558,
      "reviewText": "talk about sadness.",
      "reviewDate": "2016-12-08T07:20:53.4606463+02:00"
    },
    {
      "productId": 128,
      "reviewText": "I saw one of these in Kazakhstan and I bought one.",
      "reviewDate": "2016-11-06T02:02:39.2462601+02:00"
    },
    {
      "productId": 4586,
      "reviewText": "heard about this on folktronica radio, decided to give it a try.",
      "reviewDate": "2017-01-03T10:04:36.6613864+02:00"
    },
    {
      "productId": 4148,
      "reviewText": "It only works when I'm Wake Island.",
      "reviewDate": "2017-11-14T08:19:58.1149981+02:00"
    },
    {
      "productId": 4728,
      "reviewText": "heard about this on balearic beat radio, decided to give it a try.",
      "reviewDate": "2018-07-06T20:03:37.1764281+03:00"
    }
  ]
}