{
  "userId": 40683,
  "cartId": "dc18be5d-00c4-4b9b-aa8e-52ede2ba953e",
  "preferredProducts": [
    3110,
    3629,
    3639,
    3977
  ],
  "productReviews": [
    {
      "productId": 4316,
      "reviewText": "heard about this on smooth jazz radio, decided to give it a try.",
      "reviewDate": "2017-01-14T22:09:58.2652997+02:00"
    },
    {
      "productId": 620,
      "reviewText": "It only works when I'm Niger.",
      "reviewDate": "2018-05-05T09:03:06.1843987+03:00"
    },
    {
      "productId": 1772,
      "reviewText": "It only works when I'm Nepal.",
      "reviewDate": "2019-10-14T11:19:53.2351648+03:00"
    }
  ]
}