{
  "userId": 95707,
  "cartId": "66ae487f-ba64-4b12-8c53-455109862aa8",
  "preferredProducts": [
    4512,
    1238,
    3668,
    4711,
    2105,
    3869
  ],
  "productReviews": [
    {
      "productId": 4130,
      "reviewText": "SoCal cockroaches are unwelcome, crafty, and tenacious. This South Dakota keeps them away.",
      "reviewDate": "2018-02-27T21:23:04.1886289+02:00"
    },
    {
      "productId": 1287,
      "reviewText": "i use it barely when i'm in my store.",
      "reviewDate": "2018-07-26T10:08:22.8168067+03:00"
    },
    {
      "productId": 1725,
      "reviewText": "It only works when I'm Bahrain.",
      "reviewDate": "2017-12-28T09:38:39.4217764+02:00"
    }
  ]
}