{
  "userId": 63975,
  "cartId": "f768055f-33a3-411d-9fac-b5f86ff1bae0",
  "preferredProducts": [
    2489,
    2237,
    771,
    3223,
    4384,
    3483,
    1514,
    747,
    1602
  ],
  "productReviews": [
    {
      "productId": 3550,
      "reviewText": "My neighbor Karly has one of these. She works as a gambler and she says it looks tall.",
      "reviewDate": "2018-08-14T06:43:50.7454462+03:00"
    },
    {
      "productId": 1455,
      "reviewText": "talk about irritation.",
      "reviewDate": "2017-08-15T01:01:12.120491+03:00"
    },
    {
      "productId": 3077,
      "reviewText": "My terrier loves to play with it.",
      "reviewDate": "2017-03-07T18:18:49.6147813+02:00"
    },
    {
      "productId": 271,
      "reviewText": "I saw one of these in Nauru and I bought one.",
      "reviewDate": "2017-08-04T16:07:58.685487+03:00"
    }
  ]
}