{
  "userId": 85566,
  "cartId": "109b435d-b352-4be9-9928-53c1a0a360ad",
  "preferredProducts": [
    2173,
    462,
    76,
    1844,
    928,
    1824
  ],
  "productReviews": [
    {
      "productId": 1389,
      "reviewText": "this Rwanda is papery.",
      "reviewDate": "2017-01-14T00:38:30.8732885+02:00"
    },
    {
      "productId": 404,
      "reviewText": "one of my hobbies is antique-shopping. and when i'm antique-shopping this works great.",
      "reviewDate": "2018-01-20T10:34:52.25755+02:00"
    },
    {
      "productId": 142,
      "reviewText": "The box this comes in is 4 meter by 5 foot and weights 18 kilogram.",
      "reviewDate": "2017-03-04T10:34:06.8283296+02:00"
    },
    {
      "productId": 1236,
      "reviewText": "talk about sadness!!",
      "reviewDate": "2017-02-19T23:18:05.3491193+02:00"
    }
  ]
}