{
  "userId": 43347,
  "cartId": "3fa2e507-89a8-4827-86ab-6381973a7edb",
  "preferredProducts": [
    612,
    4945,
    3090,
    1260,
    2680,
    3783
  ],
  "productReviews": [
    {
      "productId": 1428,
      "reviewText": "I saw one of these in Sao Tome and Principe and I bought one.",
      "reviewDate": "2018-06-05T08:42:14.9273942+03:00"
    },
    {
      "productId": 4707,
      "reviewText": "It only works when I'm Nepal.",
      "reviewDate": "2019-10-22T09:04:16.2594075+03:00"
    },
    {
      "productId": 544,
      "reviewText": "This Wooden works very well. It harmonically improves my tennis by a lot.",
      "reviewDate": "2017-02-17T13:46:12.9083578+02:00"
    },
    {
      "productId": 1233,
      "reviewText": "My neighbor Victoria has one of these. She works as a professor and she says it looks menthol.",
      "reviewDate": "2016-09-15T20:40:33.9612958+03:00"
    },
    {
      "productId": 4259,
      "reviewText": "I saw one of these in Grenada and I bought one.",
      "reviewDate": "2018-12-16T02:23:53.5044135+02:00"
    }
  ]
}