{
  "userId": 31214,
  "cartId": "234aa2e3-b856-4c3a-801d-999727d84f99",
  "preferredProducts": [
    3361,
    4626,
    721
  ],
  "productReviews": [
    {
      "productId": 4864,
      "reviewText": "talk about contempt!!!",
      "reviewDate": "2018-06-17T07:32:35.3555548+03:00"
    },
    {
      "productId": 4914,
      "reviewText": "this Paradigm is revolting.",
      "reviewDate": "2019-06-22T07:17:50.3029903+03:00"
    },
    {
      "productId": 2490,
      "reviewText": "talk about contempt!",
      "reviewDate": "2018-03-09T08:49:01.350168+02:00"
    },
    {
      "productId": 4918,
      "reviewText": "This overriding works very well. It harmonically improves my tennis by a lot.",
      "reviewDate": "2019-07-05T20:26:54.6856548+03:00"
    }
  ]
}