{
  "userId": 86830,
  "cartId": "b35dbec8-bfd1-4d6a-8c5f-717ab1308d91",
  "preferredProducts": [
    4434
  ],
  "productReviews": [
    {
      "productId": 387,
      "reviewText": "heard about this on melodic death metal radio, decided to give it a try.",
      "reviewDate": "2016-08-31T14:53:49.7971774+03:00"
    },
    {
      "productId": 4429,
      "reviewText": "My co-worker Cato has one of these. He says it looks sopping.",
      "reviewDate": "2017-05-10T11:06:27.5241608+03:00"
    },
    {
      "productId": 4961,
      "reviewText": "I tried to behead it but got truffle all over it.",
      "reviewDate": "2018-12-01T06:14:09.4740809+02:00"
    }
  ]
}