{
  "userId": 75175,
  "cartId": "49f1edfc-ffc6-4180-b6a4-ff37eee798d6",
  "preferredProducts": [
    2718
  ],
  "productReviews": [
    {
      "productId": 3407,
      "reviewText": "The box this comes in is 3 inch by 6 centimeter and weights 15 ounce!",
      "reviewDate": "2020-04-18T03:37:09.540596+03:00"
    },
    {
      "productId": 3396,
      "reviewText": "i use it barely when i'm in my store.",
      "reviewDate": "2018-01-10T06:38:38.2760434+02:00"
    },
    {
      "productId": 1174,
      "reviewText": "one of my hobbies is spearfishing. and when i'm spearfishing this works great.",
      "reviewDate": "2019-05-15T02:41:15.0476455+03:00"
    },
    {
      "productId": 4436,
      "reviewText": "one of my hobbies is drawing. and when i'm drawing this works great.",
      "reviewDate": "2017-07-02T03:45:09.5874585+03:00"
    }
  ]
}