{
  "userId": 69940,
  "cartId": "309894a0-9a71-4bd8-99e3-db2749e46ee4",
  "preferredProducts": [
    2375,
    2295,
    2211,
    2295,
    2722,
    4834
  ],
  "productReviews": [
    {
      "productId": 3775,
      "reviewText": "i use it never again when i'm in my station.",
      "reviewDate": "2020-05-01T05:33:27.7289853+03:00"
    },
    {
      "productId": 2774,
      "reviewText": "i use it for 10 weeks when i'm in my jail.",
      "reviewDate": "2019-07-13T14:18:26.8097799+03:00"
    },
    {
      "productId": 1643,
      "reviewText": "My neighbor Georgie has one of these. She works as a busboy and she says it looks brown.",
      "reviewDate": "2018-08-18T09:48:34.1328095+03:00"
    },
    {
      "productId": 2316,
      "reviewText": "i use it daily when i'm in my outhouse.",
      "reviewDate": "2019-05-14T11:06:30.3303042+03:00"
    },
    {
      "productId": 1322,
      "reviewText": "I tried to vomit it but got bonbon all over it.",
      "reviewDate": "2020-02-12T14:14:44.9752266+02:00"
    }
  ]
}