{
  "userId": 61888,
  "cartId": "bb9dbe9e-d7c2-4601-a402-5794eba2b7ce",
  "preferredProducts": [
    180,
    1393,
    3373,
    422,
    4499,
    931,
    2853,
    639,
    3699
  ],
  "productReviews": [
    {
      "productId": 2079,
      "reviewText": "i use it until further notice when i'm in my nightclub.",
      "reviewDate": "2017-12-09T13:01:53.2215592+02:00"
    },
    {
      "productId": 2729,
      "reviewText": "My neighbor Victoria has one of these. She works as a professor and she says it looks menthol.",
      "reviewDate": "2017-12-04T21:48:13.882958+02:00"
    },
    {
      "productId": 853,
      "reviewText": "talk about boredom!!!",
      "reviewDate": "2019-06-07T21:31:34.4610636+03:00"
    }
  ]
}