{
  "userId": 93710,
  "cartId": "e43fa587-a947-4504-98b3-70697fce316d",
  "preferredProducts": [],
  "productReviews": [
    {
      "productId": 2055,
      "reviewText": "heard about this on bouyon radio, decided to give it a try.",
      "reviewDate": "2017-11-19T08:50:25.5458959+02:00"
    },
    {
      "productId": 1885,
      "reviewText": "one of my hobbies is skateboarding. and when i'm skateboarding this works great.",
      "reviewDate": "2019-08-12T03:39:43.5167374+03:00"
    },
    {
      "productId": 4731,
      "reviewText": "The box this comes in is 3 yard by 6 light-year and weights 11 megaton!!",
      "reviewDate": "2017-08-07T06:12:52.6024495+03:00"
    },
    {
      "productId": 3807,
      "reviewText": "The box this comes in is 5 yard by 6 centimeter and weights 18 gram!!",
      "reviewDate": "2017-02-19T15:45:40.6124739+02:00"
    }
  ]
}