{
  "userId": 92499,
  "cartId": "4b5cc269-8162-49cc-87c1-85e5a64d72e0",
  "preferredProducts": [
    1420,
    4355,
    4925,
    248,
    4010,
    4244,
    4833,
    4339,
    460
  ],
  "productReviews": [
    {
      "productId": 428,
      "reviewText": "talk about interest!!",
      "reviewDate": "2018-12-13T13:04:46.8688139+02:00"
    },
    {
      "productId": 2169,
      "reviewText": "I tried to behead it but got truffle all over it.",
      "reviewDate": "2020-02-13T20:14:02.2144332+02:00"
    }
  ]
}