{
  "userId": 9604,
  "cartId": "5e0b94b5-a659-4d16-8aa6-baec8ffb2287",
  "preferredProducts": [
    4791,
    1137,
    3009,
    1487,
    191,
    4806,
    4378,
    1130
  ],
  "productReviews": [
    {
      "productId": 3334,
      "reviewText": "I saw one of these in Haiti and I bought one.",
      "reviewDate": "2019-06-15T03:53:08.9424343+03:00"
    },
    {
      "productId": 514,
      "reviewText": "I tried to electrocute it but got sweetmeat all over it.",
      "reviewDate": "2019-08-22T06:31:14.9876009+03:00"
    }
  ]
}