{
  "userId": 48653,
  "cartId": "b764bf38-14a3-46f7-a633-9b417251f606",
  "preferredProducts": [
    470,
    3277,
    2584,
    2288
  ],
  "productReviews": [
    {
      "productId": 4105,
      "reviewText": "This withdrawal works certainly well. It energetically improves my golf by a lot.",
      "reviewDate": "2017-11-21T17:55:54.8971751+02:00"
    },
    {
      "productId": 2174,
      "reviewText": "I saw one of these in Juan de Nova Island and I bought one.",
      "reviewDate": "2019-09-14T16:39:21.3223795+03:00"
    },
    {
      "productId": 1299,
      "reviewText": "My co-worker Delton has one of these. He says it looks slender.",
      "reviewDate": "2017-05-21T12:24:47.4323796+03:00"
    },
    {
      "productId": 561,
      "reviewText": "heard about this on alternative dance radio, decided to give it a try.",
      "reviewDate": "2018-07-21T17:04:39.6429382+03:00"
    }
  ]
}