{
  "userId": 48289,
  "cartId": "1ed6f098-4c1c-4388-b4c6-5927dbacaf98",
  "preferredProducts": [
    577,
    1039,
    4170,
    1502,
    2006,
    4905
  ],
  "productReviews": [
    {
      "productId": 4931,
      "reviewText": "talk about anticipation!",
      "reviewDate": "2019-11-04T03:36:56.2083665+02:00"
    },
    {
      "productId": 2900,
      "reviewText": "This lavender works certainly well. It energetically improves my golf by a lot.",
      "reviewDate": "2016-09-01T05:05:52.8180998+03:00"
    }
  ]
}