{
  "userId": 48345,
  "cartId": "4b319f93-3c1e-4e59-b8ea-7dce0ff4bd44",
  "preferredProducts": [],
  "productReviews": [
    {
      "productId": 4098,
      "reviewText": "this Motorway is revolting.",
      "reviewDate": "2018-06-09T19:14:40.1465351+03:00"
    },
    {
      "productId": 973,
      "reviewText": "this orchid is top-notch.",
      "reviewDate": "2018-08-18T08:16:10.3839652+03:00"
    },
    {
      "productId": 3511,
      "reviewText": "It only works when I'm Samoa.",
      "reviewDate": "2016-11-01T05:23:11.0008344+02:00"
    },
    {
      "productId": 1252,
      "reviewText": "I saw one of these in Grenada and I bought one.",
      "reviewDate": "2016-11-07T14:35:56.3915122+02:00"
    }
  ]
}