{
  "userId": 91890,
  "cartId": "bcde2616-7835-47bc-9b3c-939498b49fdd",
  "preferredProducts": [
    348,
    4578,
    573,
    2705,
    1713,
    4656,
    2721,
    3550
  ],
  "productReviews": [
    {
      "productId": 4462,
      "reviewText": "one of my hobbies is antique-shopping. and when i'm antique-shopping this works great.",
      "reviewDate": "2017-10-11T06:14:38.3293738+03:00"
    },
    {
      "productId": 1861,
      "reviewText": "this Handmade Soft Pizza is brown.",
      "reviewDate": "2018-12-29T09:21:53.4756914+02:00"
    }
  ]
}