{
  "userId": 91620,
  "cartId": "a8f40022-ad56-4c8b-b219-493b1bbbd2c2",
  "preferredProducts": [
    2194,
    1549,
    2582,
    1749,
    229,
    2405,
    3414,
    2343,
    3985,
    1960
  ],
  "productReviews": [
    {
      "productId": 17,
      "reviewText": "My beagle loves to play with it.",
      "reviewDate": "2019-09-18T14:19:36.9807794+03:00"
    },
    {
      "productId": 2548,
      "reviewText": "My co-worker Namon has one of these. He says it looks funny-looking.",
      "reviewDate": "2019-03-10T06:19:25.3751926+02:00"
    },
    {
      "productId": 4588,
      "reviewText": "The box this comes in is 4 kilometer by 5 mile and weights 17 gram.",
      "reviewDate": "2017-06-05T16:35:12.7081016+03:00"
    },
    {
      "productId": 3822,
      "reviewText": "My co-worker Ali has one of these. He says it looks towering.",
      "reviewDate": "2016-08-20T01:12:11.4722386+03:00"
    },
    {
      "productId": 4645,
      "reviewText": "This interactive works very well. It romantically improves my football by a lot.",
      "reviewDate": "2019-05-15T00:07:01.243399+03:00"
    }
  ]
}