{
  "userId": 91182,
  "cartId": "e9c80e94-9631-4c56-a1f6-d3f346086132",
  "preferredProducts": [
    4723,
    807
  ],
  "productReviews": [
    {
      "productId": 1562,
      "reviewText": "I saw one of these in The Gambia and I bought one.",
      "reviewDate": "2018-03-02T01:23:15.5789642+02:00"
    },
    {
      "productId": 4901,
      "reviewText": "I saw one of these in Spratly Islands and I bought one.",
      "reviewDate": "2020-04-08T21:09:08.9607181+03:00"
    },
    {
      "productId": 3162,
      "reviewText": "It only works when I'm Rwanda.",
      "reviewDate": "2016-06-24T22:44:19.9954481+03:00"
    },
    {
      "productId": 1444,
      "reviewText": "My co-worker Nile has one of these. He says it looks crooked.",
      "reviewDate": "2017-02-05T06:19:57.9832093+02:00"
    }
  ]
}