{
  "userId": 73538,
  "cartId": "c3a2e7c3-5f7b-4902-a627-7c32eddffac9",
  "preferredProducts": [
    1105,
    28,
    313
  ],
  "productReviews": [
    {
      "productId": 521,
      "reviewText": "one of my hobbies is drawing. and when i'm drawing this works great.",
      "reviewDate": "2019-09-30T14:51:00.2507296+03:00"
    },
    {
      "productId": 2351,
      "reviewText": "i use it once in a while when i'm in my ring.",
      "reviewDate": "2016-05-25T05:18:11.3628705+03:00"
    },
    {
      "productId": 75,
      "reviewText": "i use it this time when i'm in my port-a-potty.",
      "reviewDate": "2017-11-06T23:45:02.8364006+02:00"
    },
    {
      "productId": 313,
      "reviewText": "this Handcrafted is ratty.",
      "reviewDate": "2017-07-08T00:23:39.5974864+03:00"
    },
    {
      "productId": 1550,
      "reviewText": "one of my hobbies is drawing. and when i'm drawing this works great.",
      "reviewDate": "2018-10-14T12:08:35.68115+03:00"
    }
  ]
}