{
  "userId": 73313,
  "cartId": "4e66c320-f5b4-4f95-ab4a-e6eb57b200ad",
  "preferredProducts": [
    4171,
    4182,
    4704,
    167
  ],
  "productReviews": [
    {
      "productId": 4368,
      "reviewText": "The box this comes in is 4 mile by 5 yard and weights 18 pound!!",
      "reviewDate": "2016-08-18T13:37:47.7796438+03:00"
    },
    {
      "productId": 3450,
      "reviewText": "My co-worker Fate has one of these. He says it looks tall.",
      "reviewDate": "2016-10-08T17:13:15.4073126+03:00"
    },
    {
      "productId": 4406,
      "reviewText": "My neighbor Elisha has one of these. She works as a fortune teller and she says it looks floppy.",
      "reviewDate": "2019-05-16T06:20:55.9905457+03:00"
    }
  ]
}