{
  "userId": 74521,
  "cartId": "3b62cdda-a09d-4c5b-b8c1-c9cc3e6773ae",
  "preferredProducts": [
    4229,
    3387,
    4227,
    2886,
    4250,
    2029,
    4881,
    2494,
    435,
    3019
  ],
  "productReviews": [
    {
      "productId": 528,
      "reviewText": "I saw one of these in Cote d'Ivoire and I bought one.",
      "reviewDate": "2018-05-19T19:14:28.567455+03:00"
    },
    {
      "productId": 870,
      "reviewText": "My goldfinch loves to play with it.",
      "reviewDate": "2017-08-20T20:16:03.9835914+03:00"
    },
    {
      "productId": 2492,
      "reviewText": "i use it occasionally when i'm in my outhouse.",
      "reviewDate": "2017-07-09T13:41:19.8548356+03:00"
    },
    {
      "productId": 1275,
      "reviewText": "i use it centenially when i'm in my greenhouse.",
      "reviewDate": "2019-11-17T13:47:44.2796694+02:00"
    }
  ]
}