{
  "userId": 96563,
  "cartId": "f7c06134-7cc2-4f78-8c01-999cc3069093",
  "preferredProducts": [
    4258,
    1705,
    4756,
    1307,
    2076,
    3498,
    3020
  ],
  "productReviews": [
    {
      "productId": 1562,
      "reviewText": "This JBOD works outstandingly well. It grudgingly improves my baseball by a lot.",
      "reviewDate": "2019-05-07T02:51:28.7038003+03:00"
    },
    {
      "productId": 3459,
      "reviewText": "one of my hobbies is sailing. and when i'm sailing this works great.",
      "reviewDate": "2019-11-23T19:32:24.2855615+02:00"
    },
    {
      "productId": 1412,
      "reviewText": "My co-worker Erick has one of these. He says it looks fluffy.",
      "reviewDate": "2019-05-28T04:27:51.45713+03:00"
    }
  ]
}