{
  "userId": 96606,
  "cartId": "cffe34c4-a477-4606-805c-0d87078f94e3",
  "preferredProducts": [
    984,
    4782,
    3788,
    2000,
    4475,
    4914,
    603
  ],
  "productReviews": [
    {
      "productId": 413,
      "reviewText": "My neighbor Lonnie has one of these. She works as a hobbit and she says it looks microscopic.",
      "reviewDate": "2019-04-12T22:27:12.3479886+03:00"
    },
    {
      "productId": 3330,
      "reviewText": "It only works when I'm Cook Islands.",
      "reviewDate": "2017-01-17T17:48:55.620531+02:00"
    }
  ]
}