{
  "userId": 2729,
  "cartId": "ce877ca3-46d8-447b-a3d9-3429d8ac03d5",
  "preferredProducts": [
    233,
    4898,
    3396,
    1923,
    3504,
    3502,
    2027,
    1496,
    1543,
    4322
  ],
  "productReviews": [
    {
      "productId": 2547,
      "reviewText": "heard about this on hip-hop music radio, decided to give it a try.",
      "reviewDate": "2020-04-29T12:46:19.2734861+03:00"
    },
    {
      "productId": 4198,
      "reviewText": "i use it once in a while when i'm in my ring.",
      "reviewDate": "2017-08-04T02:17:52.562494+03:00"
    },
    {
      "productId": 2986,
      "reviewText": "The box this comes in is 5 light-year by 6 foot and weights 17 megaton!!!",
      "reviewDate": "2016-07-14T21:16:30.7417168+03:00"
    },
    {
      "productId": 1878,
      "reviewText": "one of my hobbies is cooking. and when i'm cooking this works great.",
      "reviewDate": "2018-11-23T16:30:44.4108964+02:00"
    },
    {
      "productId": 2245,
      "reviewText": "talk about sadness.",
      "reviewDate": "2018-02-28T12:03:00.5605871+02:00"
    }
  ]
}