{
  "userId": 58804,
  "cartId": "47887e9b-b1fe-4ad6-b192-b59a14d37a09",
  "preferredProducts": [
    4141,
    639,
    3120,
    3342,
    4680,
    3887,
    1717,
    2478,
    2152
  ],
  "productReviews": [
    {
      "productId": 460,
      "reviewText": "My terrier loves to play with it.",
      "reviewDate": "2016-06-15T18:58:57.5869348+03:00"
    },
    {
      "productId": 4227,
      "reviewText": "This Beauty, Kids & Kids works so well. It delightedly improves my football by a lot.",
      "reviewDate": "2017-04-12T07:57:07.8785279+03:00"
    }
  ]
}