{
  "userId": 58082,
  "cartId": "f84216a6-abac-488b-aaae-4cc2efe153a6",
  "preferredProducts": [
    1611,
    4834,
    1967,
    139,
    1736,
    782
  ],
  "productReviews": [
    {
      "productId": 65,
      "reviewText": "My scarab beetle loves to play with it.",
      "reviewDate": "2017-04-18T05:16:38.7875254+03:00"
    },
    {
      "productId": 3331,
      "reviewText": "i use it until further notice when i'm in my station.",
      "reviewDate": "2019-02-21T07:41:56.2947902+02:00"
    },
    {
      "productId": 133,
      "reviewText": "The box this comes in is 5 kilometer by 6 meter and weights 20 ounce!",
      "reviewDate": "2018-04-26T08:26:34.6888769+03:00"
    },
    {
      "productId": 2188,
      "reviewText": "heard about this on gypsy jazz radio, decided to give it a try.",
      "reviewDate": "2017-08-07T13:30:30.2256102+03:00"
    },
    {
      "productId": 1001,
      "reviewText": "It only works when I'm Chad.",
      "reviewDate": "2020-04-25T15:10:51.1390468+03:00"
    }
  ]
}