{
  "userId": 35725,
  "cartId": "239b7e03-d665-4065-a9b1-dc39e10d0602",
  "preferredProducts": [
    3236,
    298,
    3627,
    2687,
    615,
    223,
    4472,
    327
  ],
  "productReviews": [
    {
      "productId": 2144,
      "reviewText": "The box this comes in is 4 light-year by 5 inch and weights 11 megaton!!",
      "reviewDate": "2020-04-19T05:24:22.1341921+03:00"
    },
    {
      "productId": 23,
      "reviewText": "I tried to cremate it but got Turkish Delight all over it.",
      "reviewDate": "2018-01-05T14:46:33.5846692+02:00"
    },
    {
      "productId": 678,
      "reviewText": "It only works when I'm Bolivia.",
      "reviewDate": "2016-12-06T15:58:20.3276005+02:00"
    }
  ]
}