{
  "userId": 94178,
  "cartId": "dac0194f-ab61-43c5-94b8-35d001caa925",
  "preferredProducts": [
    3694,
    323,
    2598,
    4799,
    1713,
    4309,
    2744,
    551,
    1915
  ],
  "productReviews": [
    {
      "productId": 1376,
      "reviewText": "i use it every Tuesday when i'm in my homeless shelter.",
      "reviewDate": "2019-10-23T04:58:51.4126761+03:00"
    },
    {
      "productId": 1922,
      "reviewText": "this Bedfordshire is awesome.",
      "reviewDate": "2019-01-12T23:37:18.7272575+02:00"
    }
  ]
}