{
  "userId": 90601,
  "cartId": "9df634c1-40ca-4a12-9ab6-70f27301a0db",
  "preferredProducts": [
    116,
    1166,
    853,
    1224,
    1345,
    2287,
    2071
  ],
  "productReviews": [
    {
      "productId": 613,
      "reviewText": "I saw one of these in Sao Tome and Principe and I bought one.",
      "reviewDate": "2018-03-23T06:50:13.3179219+02:00"
    },
    {
      "productId": 995,
      "reviewText": "It only works when I'm Samoa.",
      "reviewDate": "2017-07-08T13:54:46.4050022+03:00"
    },
    {
      "productId": 2178,
      "reviewText": "I tried to kidnap it but got apricot all over it.",
      "reviewDate": "2016-06-11T07:09:20.7983339+03:00"
    },
    {
      "productId": 3703,
      "reviewText": "The box this comes in is 3 inch by 6 centimeter and weights 15 ounce!",
      "reviewDate": "2017-02-15T10:07:57.113059+02:00"
    }
  ]
}