{
  "userId": 90679,
  "cartId": "10fcdd74-1080-4cbd-80e3-59dd4b1998ef",
  "preferredProducts": [
    4870,
    3046,
    533,
    4427,
    1288,
    4169
  ],
  "productReviews": [
    {
      "productId": 3083,
      "reviewText": "heard about this on balearic beat radio, decided to give it a try.",
      "reviewDate": "2019-12-15T05:17:08.2813994+02:00"
    },
    {
      "productId": 236,
      "reviewText": "this Flat is complimentary.",
      "reviewDate": "2018-06-30T16:17:07.9532597+03:00"
    },
    {
      "productId": 1087,
      "reviewText": "This copy works very well. It romantically improves my football by a lot.",
      "reviewDate": "2018-11-07T22:08:05.2675027+02:00"
    }
  ]
}