{
  "userId": 90594,
  "cartId": "c629a0f2-3b45-4907-82d3-d8e2bae8fbca",
  "preferredProducts": [
    723,
    1830,
    1312,
    2394,
    1040,
    3946,
    4730
  ],
  "productReviews": [
    {
      "productId": 3274,
      "reviewText": "talk about contempt!",
      "reviewDate": "2019-09-17T19:22:47.4939785+03:00"
    },
    {
      "productId": 983,
      "reviewText": "this Point is top-notch.",
      "reviewDate": "2017-11-25T13:04:55.7737812+02:00"
    },
    {
      "productId": 3791,
      "reviewText": "one of my hobbies is spearfishing. and when i'm spearfishing this works great.",
      "reviewDate": "2017-09-20T15:47:39.8556504+03:00"
    },
    {
      "productId": 4164,
      "reviewText": "My neighbor Montserrat has one of these. She works as a circus performer and she says it looks shriveled.",
      "reviewDate": "2018-02-15T10:10:59.8781446+02:00"
    },
    {
      "productId": 3338,
      "reviewText": "The box this comes in is 4 mile by 5 yard and weights 18 pound!!",
      "reviewDate": "2020-02-18T07:33:22.9231233+02:00"
    }
  ]
}