{
  "userId": 26699,
  "cartId": "f468a034-0399-4834-a7fa-c4909824e9df",
  "preferredProducts": [
    2242,
    4450,
    2242,
    1825
  ],
  "productReviews": [
    {
      "productId": 1001,
      "reviewText": "this Viaduct is standard.",
      "reviewDate": "2018-08-11T14:25:27.3730713+03:00"
    },
    {
      "productId": 4614,
      "reviewText": "heard about this on original pilipino music radio, decided to give it a try.",
      "reviewDate": "2017-03-26T09:30:54.8947187+03:00"
    },
    {
      "productId": 1659,
      "reviewText": "It only works when I'm New Caledonia.",
      "reviewDate": "2018-10-21T03:39:38.9106204+03:00"
    },
    {
      "productId": 1174,
      "reviewText": "My macaroni penguin loves to play with it.",
      "reviewDate": "2018-06-28T19:06:48.207869+03:00"
    },
    {
      "productId": 3956,
      "reviewText": "It only works when I'm Kuwait.",
      "reviewDate": "2017-03-05T04:43:17.7499141+02:00"
    }
  ]
}