{
  "userId": 77562,
  "cartId": "6beb6c0a-bafe-4dba-a1f9-75d4984618fa",
  "preferredProducts": [
    1,
    3219,
    2201,
    889,
    226,
    3235,
    1250,
    3199,
    4790
  ],
  "productReviews": [
    {
      "productId": 3590,
      "reviewText": "My neighbor Alida has one of these. She works as a gambler and she says it looks spotless.",
      "reviewDate": "2019-04-04T02:51:23.3871169+03:00"
    },
    {
      "productId": 799,
      "reviewText": "My neighbor Isabela has one of these. She works as a taxidermist and she says it looks monochromatic.",
      "reviewDate": "2016-09-11T04:10:56.9713079+03:00"
    },
    {
      "productId": 731,
      "reviewText": "It only works when I'm Juan de Nova Island.",
      "reviewDate": "2019-12-16T17:12:55.9513654+02:00"
    }
  ]
}