{
  "userId": 77864,
  "cartId": "08ffe500-0a66-429b-8e39-06bf2dfbfe7b",
  "preferredProducts": [],
  "productReviews": [
    {
      "productId": 3813,
      "reviewText": "The box this comes in is 5 yard by 6 centimeter and weights 12 kilogram.",
      "reviewDate": "2019-06-02T04:49:26.5650974+03:00"
    },
    {
      "productId": 3418,
      "reviewText": "one of my hobbies is guitar. and when i'm playing guitar this works great.",
      "reviewDate": "2018-07-22T21:14:55.6401931+03:00"
    },
    {
      "productId": 4678,
      "reviewText": "i use it biweekly when i'm in my greenhouse.",
      "reviewDate": "2019-10-29T06:21:29.8381549+02:00"
    },
    {
      "productId": 513,
      "reviewText": "I saw one of these in Canada and I bought one.",
      "reviewDate": "2018-06-29T21:08:12.8349831+03:00"
    }
  ]
}