{
  "userId": 77911,
  "cartId": "f6afd12c-2e2c-484d-9aa5-b761f4743d11",
  "preferredProducts": [
    3167
  ],
  "productReviews": [
    {
      "productId": 3758,
      "reviewText": "The box this comes in is 3 meter by 6 yard and weights 12 pound.",
      "reviewDate": "2018-10-24T15:22:35.7397409+03:00"
    },
    {
      "productId": 3748,
      "reviewText": "SoCal cockroaches are unwelcome, crafty, and tenacious. This Assurance keeps them away.",
      "reviewDate": "2018-02-08T00:07:38.6269848+02:00"
    },
    {
      "productId": 1616,
      "reviewText": "i use it profusely when i'm in my garage.",
      "reviewDate": "2019-04-19T06:33:17.9660013+03:00"
    }
  ]
}