{
  "userId": 29401,
  "cartId": "60ae45ca-302e-4d4f-b0df-77f2945a1b83",
  "preferredProducts": [
    2379,
    3262,
    3323,
    4515,
    1606,
    1185,
    3816
  ],
  "productReviews": [
    {
      "productId": 2039,
      "reviewText": "i use it for 10 weeks when i'm in my sauna.",
      "reviewDate": "2016-09-18T10:01:38.4220693+03:00"
    },
    {
      "productId": 2679,
      "reviewText": "The box this comes in is 4 yard by 5 inch and weights 12 pound!",
      "reviewDate": "2016-09-17T22:00:49.8824729+03:00"
    },
    {
      "productId": 4564,
      "reviewText": "one of my hobbies is hiking. and when i'm hiking this works great.",
      "reviewDate": "2016-09-07T23:00:34.2937382+03:00"
    }
  ]
}