{
  "userId": 81016,
  "cartId": "824001c0-2ddf-4abf-9be5-eee3d10099a0",
  "preferredProducts": [
    2129,
    4927,
    4611,
    1616,
    1583,
    241,
    3176,
    645
  ],
  "productReviews": [
    {
      "productId": 4892,
      "reviewText": "I saw one of these in Nauru and I bought one.",
      "reviewDate": "2020-02-03T09:23:28.9500336+02:00"
    },
    {
      "productId": 4028,
      "reviewText": "The box this comes in is 3 yard by 6 yard and weights 19 pound!!!",
      "reviewDate": "2016-09-02T10:06:59.8645888+03:00"
    }
  ]
}