{
  "userId": 34407,
  "cartId": "1d706ea2-6104-41e6-a9f7-10cbdb7975ac",
  "preferredProducts": [],
  "productReviews": [
    {
      "productId": 3713,
      "reviewText": "this coherent is snowy.",
      "reviewDate": "2018-01-06T10:12:02.535673+02:00"
    },
    {
      "productId": 543,
      "reviewText": "The box this comes in is 3 centimeter by 5 kilometer and weights 13 ounce!!",
      "reviewDate": "2017-12-19T21:30:18.1199125+02:00"
    },
    {
      "productId": 544,
      "reviewText": "I tried to nab it but got salad all over it.",
      "reviewDate": "2018-07-01T18:56:06.4059828+03:00"
    },
    {
      "productId": 2216,
      "reviewText": "My dog loves to play with it.",
      "reviewDate": "2016-11-21T02:22:14.1328678+02:00"
    }
  ]
}