{
  "userId": 34310,
  "cartId": "ad22cdce-7e88-417a-a6ba-762ced473948",
  "preferredProducts": [
    2138,
    4482,
    403,
    4511,
    4949,
    491,
    3522,
    1067,
    2438
  ],
  "productReviews": [
    {
      "productId": 4821,
      "reviewText": "I tried to maul it but got onion all over it.",
      "reviewDate": "2019-03-07T21:07:11.1160068+02:00"
    },
    {
      "productId": 3815,
      "reviewText": "The box this comes in is 5 kilometer by 5 inch and weights 13 kilogram!!!",
      "reviewDate": "2017-10-17T19:30:30.4015075+03:00"
    },
    {
      "productId": 4815,
      "reviewText": "My co-worker Houston has one of these. He says it looks invisible.",
      "reviewDate": "2018-12-16T00:59:36.2728922+02:00"
    }
  ]
}